<renderingStyle name="Historical" depends="default" defaultColor="#f1eae4" version="1">

	
	<order>
	</order>


	<text>
	</text>


	<point>
	</point>


	<polygon>
	    <group>
			<filter minzoom="9" color="#c98252" tag="historic" value="archaeological_site"/>
			<filter minzoom="9" color="#c98252" tag="historic" value="ruins"/>
			<filter minzoom="9" color="#c98252" tag="historic" value="battlefield"/>
			<groupFilter nightMode="true" color="#6b452b" shader=""/>
		</group>
	</polygon>


	<line>
		

	</line>

</renderingStyle>
